LICENSE
README.md
pyproject.toml
geomappy/__init__.py
geomappy/bounds.py
geomappy/colorizer.py
geomappy/colors.py
geomappy/legends.py
geomappy/plot_utils.py
geomappy/types.py
geomappy/utils.py
geomappy.egg-info/PKG-INFO
geomappy.egg-info/SOURCES.txt
geomappy.egg-info/dependency_links.txt
geomappy.egg-info/requires.txt
geomappy.egg-info/top_level.txt
geomappy/integration/__init__.py
geomappy/integration/geopandas.py
geomappy/integration/rioxarray.py
geomappy/plotting/__init__.py
geomappy/plotting/raster.py
geomappy/plotting/shapes.py
tests/test_colorizer.py
tests/test_colors.py
tests/test_legends.py
tests/test_plot_utils.py