Metadata-Version: 2.4
Name: geomappy
Version: 0.1.1
Summary: Plotting geospatial vector and raster data on a basemap using matplotlib and cartopy
Author-email: jasperroebroek <roebroek.jasper@gmail.com>
License: MIT License
Project-URL: Homepage, https://github.com/jasperroebroek/geomappy
Project-URL: Bug Tracker, https://github.com/jasperroebroek/geomappy/issues
Classifier: Programming Language :: Python :: 3
Classifier: Programming Language :: Python :: 3.10
Classifier: Programming Language :: Python :: 3.11
Classifier: Programming Language :: Python :: 3.12
Classifier: License :: OSI Approved :: GNU General Public License v3 (GPLv3)
Classifier: Operating System :: OS Independent
Requires-Python: >=3.10
License-File: LICENSE
Requires-Dist: cartopy>=0.22
Requires-Dist: rioxarray
Requires-Dist: geopandas
Requires-Dist: matplotlib>=3.10
Provides-Extra: dev
Requires-Dist: sphinx; extra == "dev"
Requires-Dist: sphinx_rtd_theme; extra == "dev"
Requires-Dist: numpydoc; extra == "dev"
Requires-Dist: jupyter; extra == "dev"
Requires-Dist: pytest; extra == "dev"
Requires-Dist: libgdal-hdf5; extra == "dev"
Dynamic: license-file
